hey/__init__.py
hey/__main__.py
hey/api.py
hey/cli.py
hey/config.py
hey/memory.py
hey/models.py
hey_py-0.1.3.dist-info/METADATA
hey_py-0.1.3.dist-info/WHEEL
hey_py-0.1.3.dist-info/entry_points.txt
hey_py-0.1.3.dist-info/top_level.txt
hey_py-0.1.3.dist-info/RECORD
