Metadata-Version: 2.4
Name: hey-py
Version: 0.1.3
Summary: A command-line tool to interact with DuckDuckGo Chat API from your terminal
Home-page: https://github.com/leen2233/hey-py
Author: Arslan Rejepow
Author-email: leen2233 <arslanrejepow223@gmail.com>
Project-URL: Homepage, https://github.com/leen2233/hey-py
Project-URL: Bug Tracker, https://github.com/leen2233/hey-py/issues
Classifier: Development Status :: 4 - Beta
Classifier: Environment :: Console
Classifier: Intended Audience :: Developers
Classifier: License :: OSI Approved :: GNU General Public License v3 (GPLv3)
Classifier: Operating System :: OS Independent
Classifier: Programming Language :: Python :: 3
Classifier: Programming Language :: Python :: 3.8
Classifier: Programming Language :: Python :: 3.9
Classifier: Programming Language :: Python :: 3.10
Classifier: Programming Language :: Python :: 3.11
Classifier: Topic :: Software Development :: Libraries :: Python Modules
Classifier: Topic :: Internet :: WWW/HTTP :: Dynamic Content
Classifier: Topic :: Utilities
Requires-Python: >=3.8
Requires-Dist: httpx[socks]<0.28,>=0.24.1
Requires-Dist: toml>=0.10.2
Requires-Dist: rich>=13.7.0
Requires-Dist: click>=8.1.7
Requires-Dist: InquirerPy
Dynamic: author
Dynamic: home-page
Dynamic: requires-python
